escpos/__init__.py
escpos/asc.py
escpos/barcode.py
escpos/config.py
escpos/constants.py
escpos/exceptions.py
escpos/feature.py
escpos/helpers.py
escpos/retry.py
escpos/showcase.py
escpos/conn/__init__.py
escpos/conn/bt.py
escpos/conn/dummy.py
escpos/conn/file.py
escpos/conn/network.py
escpos/conn/serial.py
escpos/conn/usb.py
escpos/impl/__init__.py
escpos/impl/bematech.py
escpos/impl/controlid.py
escpos/impl/daruma.py
escpos/impl/elgin.py
escpos/impl/epson.py
escpos/impl/nitere.py
escpos/impl/unknown.py
PyESCPOS-0.4.dist-info/LICENSE
PyESCPOS-0.4.dist-info/METADATA
PyESCPOS-0.4.dist-info/WHEEL
PyESCPOS-0.4.dist-info/top_level.txt
PyESCPOS-0.4.dist-info/RECORD
