Metadata-Version: 2.1
Name: PyESCPOS
Version: 0.4
Summary: Support for Epson ESC/POS printer command system.
Home-page: http://github.com/base4sistemas/pyescpos/
Author: Daniel Gonçalves
Author-email: daniel@base4.com.br
License: Apache Software License
Platform: any
Classifier: Development Status :: 4 - Beta
Classifier: Environment :: Other Environment
Classifier: Intended Audience :: Developers
Classifier: Intended Audience :: Information Technology
Classifier: License :: OSI Approved :: Apache Software License
Classifier: Natural Language :: English
Classifier: Operating System :: OS Independent
Classifier: Programming Language :: Python
Classifier: Programming Language :: Python :: 2.7
Classifier: Programming Language :: Python :: 3.6
Classifier: Programming Language :: Python :: 3.7
Classifier: Programming Language :: Python :: 3.8
Classifier: Programming Language :: Python :: 3.9
Classifier: Topic :: Printing
Classifier: Topic :: Software Development :: Libraries :: Python Modules
Classifier: Topic :: Office/Business :: Financial :: Point-Of-Sale
Requires-Dist: future
Requires-Dist: six
Provides-Extra: bluetooth
Requires-Dist: PyBluez ; extra == 'bluetooth'
Provides-Extra: serial
Requires-Dist: pySerial ; extra == 'serial'
Provides-Extra: usb
Requires-Dist: PyUSB ; extra == 'usb'
